telegram_retriever/__init__.py
telegram_retriever/client.py
telegram_retriever/retriever.py
telegram_retriever-0.1.4.dist-info/METADATA
telegram_retriever-0.1.4.dist-info/WHEEL
telegram_retriever-0.1.4.dist-info/licenses/LICENSE
telegram_retriever-0.1.4.dist-info/RECORD
