Metadata-Version: 2.4
Name: telegram-retriever
Version: 0.1.4
Summary: A Human-in-the-Loop retriever for LangChain that pauses execution to wait for a Telegram reply.
Project-URL: Documentation, https://github.com/l3onlau/telegram-retriever#readme
Project-URL: Issues, https://github.com/l3onlau/telegram-retriever/issues
Project-URL: Source, https://github.com/l3onlau/telegram-retriever
Author: l3onlau
License: Copyright (c) 2025 l3onlau
License-File: LICENSE
Keywords: agent,human-in-the-loop,langchain,retriever,telegram
Classifier: Development Status :: 4 - Beta
Classifier: Intended Audience :: Developers
Classifier: License :: OSI Approved :: MIT License
Classifier: Programming Language :: Python :: 3.9
Classifier: Programming Language :: Python :: 3.10
Classifier: Programming Language :: Python :: 3.11
Classifier: Programming Language :: Python :: 3.12
Classifier: Topic :: Software Development :: Libraries :: Python Modules
Requires-Python: >=3.9
Requires-Dist: httpx>=0.24.0
Requires-Dist: langchain-core>=0.1.0
Requires-Dist: pydantic>=2.0.0
Provides-Extra: test
Requires-Dist: pytest; extra == 'test'
Requires-Dist: pytest-asyncio; extra == 'test'
Requires-Dist: pytest-mock; extra == 'test'
